wayland/__about__.py
wayland/__init__.py
wayland/__init__.pyi
wayland/__main__.py
wayland/constants.py
wayland/log.py
wayland/parser.py
wayland/protocols.json
wayland/proxy.py
wayland/state.py
wayland/unixsocket.py
libwayland-0.3.0.dist-info/METADATA
libwayland-0.3.0.dist-info/WHEEL
libwayland-0.3.0.dist-info/licenses/LICENSE
libwayland-0.3.0.dist-info/RECORD
