Metadata-Version: 2.3
Name: libwayland
Version: 0.3.0
Summary: An implementation of the Wayland protocol with no external dependencies.
Project-URL: Homepage, https://github.com/grking/libwayland
Project-URL: Documentation, https://github.com/grking/libwayland#readme
Project-URL: Issues, https://github.com/grking/libwayland/issues
Project-URL: Source, https://github.com/grking/libwayland
Project-URL: Changelog, https://github.com/grking/libwayland/blob/main/CHANGELOG.md
Author-email: Graham King <grking.email@gmail.com>
License: MIT License
License-File: LICENSE
Classifier: Development Status :: 3 - Alpha
Classifier: Intended Audience :: Developers
Classifier: License :: OSI Approved :: MIT License
Classifier: Programming Language :: Python
Classifier: Programming Language :: Python :: 3.8
Classifier: Programming Language :: Python :: 3.9
Classifier: Programming Language :: Python :: 3.10
Classifier: Programming Language :: Python :: 3.11
Classifier: Programming Language :: Python :: 3.12
Classifier: Programming Language :: Python :: Implementation :: CPython
Requires-Python: >=3.8
Provides-Extra: build
Requires-Dist: lxml; extra == 'build'
Requires-Dist: requests; extra == 'build'
